quantumgeometrytensor/Function.py
quantumgeometrytensor/QuantumGeometry.py
quantumgeometrytensor/QuantumGeometryDipole.py
quantumgeometrytensor/__init__.py
quantumgeometrytensor-0.2.4.dist-info/METADATA
quantumgeometrytensor-0.2.4.dist-info/WHEEL
quantumgeometrytensor-0.2.4.dist-info/top_level.txt
quantumgeometrytensor-0.2.4.dist-info/RECORD
