Metadata-Version: 2.4
Name: quantumgeometrytensor
Version: 0.2.4
Summary: This is a package using calculate the quantum geometry including Zeeman QGT, S_QGT as well as the corresponding dipole quantities
Home-page: https://github.com/jiajinxiong/QuantumGeometryTensor
Author: JinxiongJia
Author-email: jiajinxiong0402@126.com
Requires-Python: >=3.7
Requires-Dist: numpy
Dynamic: author
Dynamic: author-email
Dynamic: description
Dynamic: description-content-type
Dynamic: home-page
Dynamic: requires-dist
Dynamic: requires-python
Dynamic: summary
